LICENSE
MANIFEST.in
README.md
setup.py
requirements/install.txt
requirements/tests.txt
wpparser/__init__.py
wpparser/parser.py
wpparser.egg-info/PKG-INFO
wpparser.egg-info/SOURCES.txt
wpparser.egg-info/dependency_links.txt
wpparser.egg-info/not-zip-safe
wpparser.egg-info/requires.txt
wpparser.egg-info/top_level.txt