Metadata-Version: 1.1
Name: wpparser
Version: 1.0.6
Summary: Parse wordpress export files into a well formatted python dictionary
Home-page: https://github.com/marteinn/wpparser
Author: Martin Sandström
Author-email: martin@marteinn.se
License: MIT
Platform: UNKNOWN
Classifier: Development Status :: 4 - Beta
Classifier: Intended Audience :: Developers
Classifier: Natural Language :: English
Classifier: License :: OSI Approved :: MIT License
Classifier: Programming Language :: Python
Classifier: Programming Language :: Python :: 2.7
